Metadata-Version: 1.0
Name: ali-gaussbinom-distributions
Version: 1.0
Summary: Gaussian and Binomial distributions
Home-page: UNKNOWN
Author: Ali Zeynalli
Author-email: UNKNOWN
License: UNKNOWN
Platform: UNKNOWN
